<environment>
    <camtrans>1.214623 0.559342 1.580332</camtrans>
    <camrotationaxis>-0.413015 -0.784243 0.463013 146.112354</camrotationaxis>
    <camfocal>1.492339</camfocal>

    <kinbody name="floor">
        <body type="static">
            <translation>0 0 -.5</translation>
            <geom type="box">
                <extents>5 5 .5</extents>
                <diffusecolor>.81 .4 .4</diffusecolor>
                <ambientcolor>0.4 0.5 0.6</ambientcolor>
            </geom>
        </body>
    </kinbody>

    <kinbody name="hydrant_vertical" file="../kinbody/hydrant.kinbody.xml">
        <translation>0.23524 0.1 1.27435 </translation>
    </kinbody>

    <kinbody name="hose" file="../kinbody/hose.kinbody.xml">
        <!--Hubo+ location, left hand-->
        <translation>0.278 0.161 1.138</translation>
        <mass type="mimicgeom">
            <total>1</total>
        </mass>
    </kinbody>
</environment>
